[
  {
    "url": "https://www.youtube.com/watch?v=_m2bFhFrAwQ&list=RDQmBzRhtqrEE&index=23",
    "filename": "Tải âm thanh thành công!",
    "timestamp": "2025-06-09T22:48:31.753774"
  },
  {
    "url": "https://www.youtube.com/watch?v=L727ev0q6pA&list=RDQmBzRhtqrEE&index=26&pp=8AUB",
    "filename": "Tải âm thanh thành công!",
    "timestamp": "2025-06-09T22:49:19.331575"
  },
  {
    "url": "https://www.youtube.com/watch?v=6ZYf-vwZ1Uw&list=RDQmBzRhtqrEE&index=27&pp=8AUB",
    "filename": "Tải âm thanh thành công!",
    "timestamp": "2025-06-09T22:49:26.329230"
  },
  {
    "url": "https://www.youtube.com/watch?v=L727ev0q6pA&list=RDQmBzRhtqrEE&index=26&pp=8AUB",
    "filename": "Tải âm thanh thành công!",
    "timestamp": "2025-06-09T22:52:57.511917"
  }
]